<?xml version="1.0" encoding="UTF-8" standalone="no"?>
<knowtator-project>
  <profile id="Default">
    <highlighter class="" color="#00ffff"/>
    <highlighter class="opposing_findings" color="#ffcccc"/>
    <highlighter class="unproven_efficacy" color="#ffff00"/>
    <highlighter class="recognized" color="#00ffff"/>
    <highlighter class="limited_evidence" color="#ffff00"/>
    <highlighter class="explanation" color="#00ffff"/>
    <highlighter class="longer_term_follow-up_is_needed" color="#ccffcc"/>
    <highlighter class="would" color="#ccffcc"/>
    <highlighter class="depending_on" color="#00ffff"/>
    <highlighter class="poor" color="#00ffff"/>
    <highlighter class="no_clear" color="#00ffff"/>
    <highlighter class="very_little" color="#ffff00"/>
    <highlighter class="because" color="#00ffff"/>
    <highlighter class="few...studies" color="#ffff00"/>
    <highlighter class="failed_to_reveal" color="#ffff00"/>
    <highlighter class="unlikely" color="#ffff00"/>
    <highlighter class="data...are_sparse" color="#ffff00"/>
    <highlighter class="not_yet_been_determined" color="#ffff00"/>
    <highlighter class="thus" color="#00ffff"/>
    <highlighter class="notably" color="#ccccff"/>
    <highlighter class="not_been_conducted" color="#ffff00"/>
    <highlighter class="models" color="#ffff00"/>
    <highlighter class="coincide" color="#ffff00"/>
    <highlighter class="require" color="#ccffcc"/>
    <highlighter class="to_the_best_of_our_knowledge" color="#00ffff"/>
    <highlighter class="apparent" color="#ccccff"/>
    <highlighter class="evidence_is_mounting" color="#ffff00"/>
    <highlighter class="not...proven" color="#ffff00"/>
    <highlighter class="correlation" color="#ffff00"/>
    <highlighter class="further_testing" color="#ccffcc"/>
    <highlighter class="some_evidence" color="#ffff00"/>
    <highlighter class="but_others" color="#ffcccc"/>
    <highlighter class="ongoing_debate" color="#ffcccc"/>
    <highlighter class="protective" color="#00ffff"/>
    <highlighter class="though" color="#ccccff"/>
    <highlighter class="appears_to_be" color="#ccccff"/>
    <highlighter class="?" color="#00ffff"/>
    <highlighter class="warrant_further_investigation" color="#ccffcc"/>
    <highlighter class="there_is_evidence" color="#ffff00"/>
    <highlighter class="association" color="#00ffff"/>
    <highlighter class="role" color="#00ffff"/>
    <highlighter class="independent" color="#00ffff"/>
    <highlighter class="concluded" color="#00ffff"/>
    <highlighter class="showed" color="#00ffff"/>
    <highlighter class="debated" color="#ffcccc"/>
    <highlighter class="adjustment_is_needed" color="#ccffcc"/>
    <highlighter class="whether_or_not" color="#ffff00"/>
    <highlighter class="found" color="#00ffff"/>
    <highlighter class="probably" color="#ffff00"/>
    <highlighter class="further_research" color="#ccffcc"/>
    <highlighter class="uncertainty" color="#ffff00"/>
    <highlighter class="plausible" color="#ffff00"/>
    <highlighter class="further_questions" color="#00ffff"/>
    <highlighter class="not_received_sufficient_attention" color="#ffff00"/>
    <highlighter class="variations" color="#00ffff"/>
    <highlighter class="appear_to_be" color="#ccccff"/>
    <highlighter class="missed_opportunity" color="#ccffcc"/>
    <highlighter class="not_fully_explored" color="#ffff00"/>
    <highlighter class="still_being_discussed" color="#ffff00"/>
    <highlighter class="describe" color="#00ffff"/>
    <highlighter class="little_or_no" color="#00ffff"/>
    <highlighter class="linked" color="#ffff00"/>
    <highlighter class="as_with" color="#00ffff"/>
    <highlighter class="correlations" color="#00ffff"/>
    <highlighter class="increasingly_accepted" color="#ffff00"/>
    <highlighter class="full_unknown" color="#ffff00"/>
    <highlighter class="associated" color="#00ffff"/>
    <highlighter class="remains_unknown" color="#ffff00"/>
    <highlighter class="beliefs" color="#ffff00"/>
    <highlighter class="rationale" color="#00ffff"/>
    <highlighter class="plausibly" color="#ffff00"/>
    <highlighter class="received_little_study" color="#ffff00"/>
    <highlighter class="severe" color="#00ffff"/>
    <highlighter class="obvious" color="#00ffff"/>
    <highlighter class="information" color="#00ffff"/>
    <highlighter class="scarce_information" color="#ffff00"/>
    <highlighter class="novel" color="#ffff00"/>
    <highlighter class="in_general" color="#00ffff"/>
    <highlighter class="0_possible_understanding" color="#ffff00"/>
    <highlighter class="evidence" color="#00ffff"/>
    <highlighter class="little_focus" color="#ffff00"/>
    <highlighter class="strong_evidence" color="#ffff00"/>
    <highlighter class="alternative_options" color="#ffff00"/>
    <highlighter class="evidence...limited" color="#ffff00"/>
    <highlighter class="lack_of...data" color="#ffff00"/>
    <highlighter class="first_time" color="#ffff00"/>
    <highlighter class="theorized" color="#ffff00"/>
    <highlighter class="serious" color="#00ffff"/>
    <highlighter class="recent_study" color="#00ffff"/>
    <highlighter class="predicted" color="#00ffff"/>
    <highlighter class="most_commonly" color="#00ffff"/>
    <highlighter class="implicated" color="#ffff00"/>
    <highlighter class="have_been" color="#ffff00"/>
    <highlighter class="have_not_been_firmly_established" color="#ffff00"/>
    <highlighter class="whether" color="#ffff00"/>
    <highlighter class="need" color="#ffff00"/>
    <highlighter class="are_warranted" color="#ccffcc"/>
    <highlighter class="research_is_needed" color="#ccffcc"/>
    <highlighter class="often" color="#00ffff"/>
    <highlighter class="remain_a...problem" color="#ffcccc"/>
    <highlighter class="this...review" color="#00ffff"/>
    <highlighter class="contributes" color="#ffff00"/>
    <highlighter class="limited...data" color="#ffff00"/>
    <highlighter class="lack" color="#ffff00"/>
    <highlighter class="candidates" color="#00ffff"/>
    <highlighter class="do_not_fully" color="#ffff00"/>
    <highlighter class="incomplete...results" color="#ffff00"/>
    <highlighter class="claims" color="#ffff00"/>
    <highlighter class="need_to_study" color="#ccffcc"/>
    <highlighter class="alternative_approach" color="#ffff00"/>
    <highlighter class="new" color="#ffff00"/>
    <highlighter class="therefore" color="#00ffff"/>
    <highlighter class="paramount" color="#ccffcc"/>
    <highlighter class="demonstrated" color="#00ffff"/>
    <highlighter class="still_remain" color="#ffff00"/>
    <highlighter class="roles" color="#00ffff"/>
    <highlighter class="is_considered" color="#00ffff"/>
    <highlighter class="accumulating_evidence_has_shown" color="#ffff00"/>
    <highlighter class="remains...problem" color="#ffcccc"/>
    <highlighter class="emerging_field" color="#ffff00"/>
    <highlighter class="paucity" color="#ffff00"/>
    <highlighter class="inconsistencies" color="#00ffff"/>
    <highlighter class="expanded" color="#00ffff"/>
    <highlighter class="compelling_evidence" color="#ffff00"/>
    <highlighter class="previously" color="#ffff00"/>
    <highlighter class="remains_to_be_established" color="#ffff00"/>
    <highlighter class="future_work" color="#00ffff"/>
    <highlighter class="not_clear" color="#ffff00"/>
    <highlighter class="wide_spectrum" color="#ffcccc"/>
    <highlighter class="hypothesize" color="#ffff00"/>
    <highlighter class="no...identified" color="#ffff00"/>
    <highlighter class="links" color="#ffff00"/>
    <highlighter class="this...study" color="#00ffff"/>
    <highlighter class="not_based_on_scientific_evidence" color="#ffff00"/>
    <highlighter class="intersect" color="#ffff00"/>
    <highlighter class="not_been_investigated" color="#ffff00"/>
    <highlighter class="retrospective" color="#00ffff"/>
    <highlighter class="has_been...challenged" color="#ffcccc"/>
    <highlighter class="is_sparse" color="#ffff00"/>
    <highlighter class="factors" color="#00ffff"/>
    <highlighter class="better" color="#00ffff"/>
    <highlighter class="noted" color="#00ffff"/>
    <highlighter class="significance" color="#00ffff"/>
    <highlighter class="growing_interest" color="#ffff00"/>
    <highlighter class="explicit_question" color="#ffff00"/>
    <highlighter class="if_confirmed" color="#ccffcc"/>
    <highlighter class="little_to_no" color="#ffff00"/>
    <highlighter class="regardless_of" color="#00ffff"/>
    <highlighter class="rct_is...needed" color="#ccffcc"/>
    <highlighter class="need_for_replication" color="#ccffcc"/>
    <highlighter class="detected" color="#00ffff"/>
    <highlighter class="not_immediately_apparent" color="#ffff00"/>
    <highlighter class="suitable" color="#00ffff"/>
    <highlighter class="strikingly" color="#ccccff"/>
    <highlighter class="opposite_to_our_findings" color="#ffcccc"/>
    <highlighter class="this_paper" color="#ff6600"/>
    <highlighter class="inconsistency" color="#ffcccc"/>
    <highlighter class="to_test" color="#00ffff"/>
    <highlighter class="rough_indicator" color="#ffff00"/>
    <highlighter class="research_in_this_area" color="#ccffcc"/>
    <highlighter class="as_in" color="#00ffff"/>
    <highlighter class="illustrates" color="#00ffff"/>
    <highlighter class="marginal_evidence" color="#ffff00"/>
    <highlighter class="tendency" color="#00ffff"/>
    <highlighter class="considered" color="#ccffcc"/>
    <highlighter class="are_needed" color="#ccffcc"/>
    <highlighter class="focus" color="#00ffff"/>
    <highlighter class="to_determine" color="#00ffff"/>
    <highlighter class="newly" color="#ffff00"/>
    <highlighter class="issues" color="#ffcccc"/>
    <highlighter class="not...adequately" color="#ffff00"/>
    <highlighter class="variation" color="#ffcccc"/>
    <highlighter class="newly" color="#ffff00"/>
    <highlighter class="directions_for_future_research" color="#ccffcc"/>
    <highlighter class="conjecture" color="#ffff00"/>
    <highlighter class="trend" color="#00ffff"/>
    <highlighter class="not_been_explored" color="#ffff00"/>
    <highlighter class="even" color="#ccccff"/>
    <highlighter class="it_is_known" color="#ffff00"/>
    <highlighter class="continued_studies" color="#ccffcc"/>
    <highlighter class="better_understanding" color="#ffff00"/>
    <highlighter class="study...is_merited" color="#ccffcc"/>
    <highlighter class="need_to...identify" color="#ffff00"/>
    <highlighter class="recent_research" color="#ffff00"/>
    <highlighter class="often_overlooked" color="#ffff00"/>
    <highlighter class="0_model" color="#ffff00"/>
    <highlighter class="similar" color="#00ffff"/>
    <highlighter class="little_information" color="#ffff00"/>
    <highlighter class="determinants" color="#00ffff"/>
    <highlighter class="limited" color="#ffff00"/>
    <highlighter class="similar_to" color="#00ffff"/>
    <highlighter class="considering" color="#00ffff"/>
    <highlighter class="remains_under_investigation" color="#ffff00"/>
    <highlighter class="gaps_in_knowledge" color="#ffff00"/>
    <highlighter class="highly_recommended" color="#ccffcc"/>
    <highlighter class="misdiagnosed" color="#00ffff"/>
    <highlighter class="interesting_to_note" color="#ccccff"/>
    <highlighter class="required" color="#00ffff"/>
    <highlighter class="not_available" color="#ffff00"/>
    <highlighter class="putative" color="#00ffff"/>
    <highlighter class="encourage_more_research" color="#ccffcc"/>
    <highlighter class="confirmation" color="#00ffff"/>
    <highlighter class="underlying" color="#00ffff"/>
    <highlighter class="impacts" color="#ffff00"/>
    <highlighter class="still" color="#00ffff"/>
    <highlighter class="depends_on" color="#00ffff"/>
    <highlighter class="propose" color="#ffff00"/>
    <highlighter class="the_concept" color="#00ffff"/>
    <highlighter class="likelihood" color="#ffff00"/>
    <highlighter class="even" color="#ccccff"/>
    <highlighter class="to_examine" color="#ff6600"/>
    <highlighter class="incomplete_understanding" color="#ffff00"/>
    <highlighter class="has_not_been" color="#00ffff"/>
    <highlighter class="mixed_results" color="#ffcccc"/>
    <highlighter class="indicating" color="#ffff00"/>
    <highlighter class="not_well_established" color="#ffff00"/>
    <highlighter class="assumed" color="#00ffff"/>
    <highlighter class="it_is_thought" color="#ffff00"/>
    <highlighter class="in_contrast_to" color="#ffcccc"/>
    <highlighter class="no_evidence" color="#00ffff"/>
    <highlighter class="hypotheses" color="#ffff00"/>
    <highlighter class="wide_range" color="#ffcccc"/>
    <highlighter class="other" color="#00ffff"/>
    <highlighter class="previously_thought" color="#ffcccc"/>
    <highlighter class="has_been_mounting_evidence" color="#ffff00"/>
    <highlighter class="aim" color="#ff6600"/>
    <highlighter class="indicated" color="#ffff00"/>
    <highlighter class="uncommonly" color="#ffff00"/>
    <highlighter class="if_so" color="#ccffcc"/>
    <highlighter class="alternate_hypotheses" color="#ffff00"/>
    <highlighter class="need_for_additional_interventions" color="#ccffcc"/>
    <highlighter class="related" color="#00ffff"/>
    <highlighter class="mandatory" color="#ccffcc"/>
    <highlighter class="variability" color="#ffcccc"/>
    <highlighter class="valid" color="#00ffff"/>
    <highlighter class="indicating" color="#ffff00"/>
    <highlighter class="asked" color="#ffff00"/>
    <highlighter class="encourage" color="#ccffcc"/>
    <highlighter class="indicates" color="#ffff00"/>
    <highlighter class="aim" color="#ff6600"/>
    <highlighter class="hypotheses" color="#ffff00"/>
    <highlighter class="further_consideration" color="#ccffcc"/>
    <highlighter class="one_study" color="#00ffff"/>
    <highlighter class="imperative" color="#ccffcc"/>
    <highlighter class="assumed" color="#00ffff"/>
    <highlighter class="has...been" color="#00ffff"/>
    <highlighter class="several...studies" color="#00ffff"/>
    <highlighter class="designed_to" color="#ff6600"/>
    <highlighter class="incidentally" color="#ccccff"/>
    <highlighter class="accordingly" color="#00ffff"/>
    <highlighter class="whether...and" color="#ffff00"/>
    <highlighter class="consequence" color="#00ffff"/>
    <highlighter class="implications" color="#00ffff"/>
    <highlighter class="robust" color="#00ffff"/>
    <highlighter class="particularly" color="#00ffff"/>
    <highlighter class="question" color="#ffff00"/>
    <highlighter class="attributed" color="#00ffff"/>
    <highlighter class="has_been_questioned" color="#ffcccc"/>
    <highlighter class="than_previously_predicted" color="#ffcccc"/>
    <highlighter class="needed_in_future_studies" color="#ccffcc"/>
    <highlighter class="inconsistent" color="#ffcccc"/>
    <highlighter class="opportunities" color="#ccffcc"/>
    <highlighter class="correlates" color="#00ffff"/>
    <highlighter class="tended" color="#00ffff"/>
    <highlighter class="data...limited" color="#ffff00"/>
    <highlighter class="hard-to-reach" color="#ffcccc"/>
    <highlighter class="future" color="#ccffcc"/>
    <highlighter class="is_needed" color="#00ffff"/>
    <highlighter class="differences" color="#00ffff"/>
    <highlighter class="the_only_other_published_report" color="#ffff00"/>
    <highlighter class="this_review" color="#00ffff"/>
    <highlighter class="urgently" color="#ccffcc"/>
    <highlighter class="surprisingly" color="#00ffff"/>
    <highlighter class="similar_to" color="#00ffff"/>
    <highlighter class="other" color="#00ffff"/>
    <highlighter class="evidence-based" color="#ffff00"/>
    <highlighter class="high_priority" color="#ccffcc"/>
    <highlighter class="possibilities" color="#ffff00"/>
    <highlighter class="more...strategies" color="#ccffcc"/>
    <highlighter class="subject_scope" color="#00ffff"/>
    <highlighter class="0_difficult_task" color="#ffcccc"/>
    <highlighter class="findings" color="#00ffff"/>
    <highlighter class="noted" color="#00ffff"/>
    <highlighter class="prevents" color="#00ffff"/>
    <highlighter class="to_assess" color="#00ffff"/>
    <highlighter class="further_avenues" color="#ccffcc"/>
    <highlighter class="associate" color="#ffff00"/>
    <highlighter class="has_been_suggested" color="#ffff00"/>
    <highlighter class="influence" color="#00ffff"/>
    <highlighter class="remained" color="#00ffff"/>
    <highlighter class="mainly" color="#ffff00"/>
    <highlighter class="varies" color="#ffcccc"/>
    <highlighter class="little_conclusive_evidence" color="#ffff00"/>
    <highlighter class="need" color="#ffff00"/>
    <highlighter class="whether" color="#ffff00"/>
    <highlighter class="plausibility" color="#ffff00"/>
    <highlighter class="study...is_needed" color="#ccffcc"/>
    <highlighter class="links" color="#ffff00"/>
    <highlighter class="earlier_studies" color="#ffff00"/>
    <highlighter class="should_be" color="#ccffcc"/>
    <highlighter class="suggesting" color="#00ffff"/>
    <highlighter class="considerable_scientific_evidence" color="#ffff00"/>
    <highlighter class="correlated" color="#00ffff"/>
    <highlighter class="well-known" color="#00ffff"/>
    <highlighter class="growing_body_of_literature" color="#ffff00"/>
    <highlighter class="unique_opportunities" color="#ccffcc"/>
    <highlighter class="new" color="#ffff00"/>
    <highlighter class="prudent" color="#ccffcc"/>
    <highlighter class="first_study" color="#ffff00"/>
    <highlighter class="consistent" color="#00ffff"/>
    <highlighter class="involved" color="#ffff00"/>
    <highlighter class="have_also_been_found" color="#ffff00"/>
    <highlighter class="cannot_rule_out" color="#ffff00"/>
    <highlighter class="taboos" color="#ffcccc"/>
    <highlighter class="immediate_need" color="#ccffcc"/>
    <highlighter class="less" color="#00ffff"/>
    <highlighter class="affected" color="#ffff00"/>
    <highlighter class="differed" color="#00ffff"/>
    <highlighter class="conflicting" color="#ffcccc"/>
    <highlighter class="driving" color="#00ffff"/>
    <highlighter class="study_is_ongoing" color="#ffff00"/>
    <highlighter class="complexities" color="#ffcccc"/>
    <highlighter class="confounding_factors" color="#00ffff"/>
    <highlighter class="empirical_support" color="#ffff00"/>
    <highlighter class="rarely" color="#ffff00"/>
    <highlighter class="not_well_defined" color="#ffff00"/>
    <highlighter class="examined" color="#00ffff"/>
    <highlighter class="public_health_concerns" color="#00ffff"/>
    <highlighter class="in_line_with" color="#00ffff"/>
    <highlighter class="must...be" color="#ccffcc"/>
    <highlighter class="supportive" color="#ffff00"/>
    <highlighter class="complication" color="#ffcccc"/>
    <highlighter class="unexpectedly" color="#ccccff"/>
    <highlighter class="at_risk" color="#00ffff"/>
    <highlighter class="previously" color="#ffff00"/>
    <highlighter class="influenced" color="#00ffff"/>
    <highlighter class="unclear" color="#ffff00"/>
    <highlighter class="postulated" color="#00ffff"/>
    <highlighter class="difficulty" color="#ffcccc"/>
    <highlighter class="role" color="#00ffff"/>
    <highlighter class="represents" color="#00ffff"/>
    <highlighter class="weakness" color="#00ffff"/>
    <highlighter class="similarly" color="#00ffff"/>
    <highlighter class="little_we_know" color="#ffff00"/>
    <highlighter class="superficial_relationship" color="#ffff00"/>
    <highlighter class="influences" color="#ffff00"/>
    <highlighter class="predict" color="#00ffff"/>
    <highlighter class="paradoxically" color="#ffcccc"/>
    <highlighter class="detrimental" color="#00ffff"/>
    <highlighter class="little_data" color="#ffff00"/>
    <highlighter class="need_to_be_re-evaluated" color="#ccffcc"/>
    <highlighter class="possibility" color="#ffff00"/>
    <highlighter class="evidence...weaker" color="#ffff00"/>
    <highlighter class="plan_to" color="#00ffff"/>
    <highlighter class="not_necessarily" color="#00ffff"/>
    <highlighter class="due_to" color="#00ffff"/>
    <highlighter class="complicating" color="#ffcccc"/>
    <highlighter class="not_yet_been_examined" color="#ffff00"/>
    <highlighter class="this_experiment" color="#ff6600"/>
    <highlighter class="requirement" color="#00ffff"/>
    <highlighter class="disparities" color="#ffcccc"/>
    <highlighter class="despite" color="#ccccff"/>
    <highlighter class="relation" color="#00ffff"/>
    <highlighter class="suggested" color="#ffff00"/>
    <highlighter class="no_role" color="#ffff00"/>
    <highlighter class="several_methods" color="#ffff00"/>
    <highlighter class="suggestions_for_future_research" color="#ccffcc"/>
    <highlighter class="objectives" color="#ff6600"/>
    <highlighter class="until" color="#ccffcc"/>
    <highlighter class="to...identify" color="#00ffff"/>
    <highlighter class="which" color="#ffff00"/>
    <highlighter class="strategy" color="#00ffff"/>
    <highlighter class="hypothesis" color="#ffff00"/>
    <highlighter class="vary_substantially" color="#ffcccc"/>
    <highlighter class="little...is_known" color="#ffff00"/>
    <highlighter class="credited" color="#ffff00"/>
    <highlighter class="either...or" color="#00ffff"/>
    <highlighter class="not_clear" color="#ffff00"/>
    <highlighter class="0_controversy" color="#ffcccc"/>
    <highlighter class="determinant" color="#00ffff"/>
    <highlighter class="future_directions" color="#ccffcc"/>
    <highlighter class="thought" color="#ffff00"/>
    <highlighter class="supposed_to" color="#ffcccc"/>
    <highlighter class="not_reported" color="#00ffff"/>
    <highlighter class="unidentified" color="#00ffff"/>
    <highlighter class="of_note" color="#00ffff"/>
    <highlighter class="utmost_importance" color="#ccffcc"/>
    <highlighter class="uncertain" color="#ffff00"/>
    <highlighter class="concern" color="#00ffff"/>
    <highlighter class="differently" color="#00ffff"/>
    <highlighter class="inferring" color="#00ffff"/>
    <highlighter class="defined" color="#00ffff"/>
    <highlighter class="not_consistently" color="#ffcccc"/>
    <highlighter class="novel" color="#ffff00"/>
    <highlighter class="models" color="#ffff00"/>
    <highlighter class="indicate" color="#00ffff"/>
    <highlighter class="too...to_be" color="#00ffff"/>
    <highlighter class="remain" color="#ffff00"/>
    <highlighter class="full_unknown" color="#ffff00"/>
    <highlighter class="expected" color="#ccffcc"/>
    <highlighter class="probable" color="#ffff00"/>
    <highlighter class="opposite" color="#ffcccc"/>
    <highlighter class="found_to_be" color="#00ffff"/>
    <highlighter class="relevant_to" color="#00ffff"/>
    <highlighter class="correlations" color="#00ffff"/>
    <highlighter class="future_prediction" color="#ccffcc"/>
    <highlighter class="little_scientific_support" color="#ffff00"/>
    <highlighter class="has_yet_to_be_determined" color="#ffff00"/>
    <highlighter class="strengthens_the_evidence" color="#ffff00"/>
    <highlighter class="critically" color="#ccffcc"/>
    <highlighter class="argues" color="#ffff00"/>
    <highlighter class="because" color="#00ffff"/>
    <highlighter class="study_design_is_needed" color="#ccffcc"/>
    <highlighter class="importance" color="#ccffcc"/>
    <highlighter class="difference" color="#00ffff"/>
    <highlighter class="must" color="#ccffcc"/>
    <highlighter class="depending_on" color="#00ffff"/>
    <highlighter class="limitations" color="#ffff00"/>
    <highlighter class="incomplete_evidence" color="#ffff00"/>
    <highlighter class="predictors" color="#00ffff"/>
    <highlighter class="associations" color="#ffff00"/>
    <highlighter class="complexity" color="#ffcccc"/>
    <highlighter class="remains...challenge" color="#ffcccc"/>
    <highlighter class="argued" color="#ffff00"/>
    <highlighter class="probably" color="#ffff00"/>
    <highlighter class="maybe" color="#ffff00"/>
    <highlighter class="neglected_topic" color="#ffff00"/>
    <highlighter class="some_evidence_to_suggest" color="#ffff00"/>
    <highlighter class="another" color="#00ffff"/>
    <highlighter class="no_reports" color="#ffff00"/>
    <highlighter class="several_studies" color="#ffff00"/>
    <highlighter class="recommend" color="#ccffcc"/>
    <highlighter class="scrutiny" color="#ffcccc"/>
    <highlighter class="as" color="#00ffff"/>
    <highlighter class="plausible" color="#ffff00"/>
    <highlighter class="whether_or_not" color="#ffff00"/>
    <highlighter class="notion" color="#ffff00"/>
    <highlighter class="found" color="#00ffff"/>
    <highlighter class="poorly_characterized" color="#ffff00"/>
    <highlighter class="not_fully_understood" color="#ffff00"/>
    <highlighter class="varying" color="#00ffff"/>
    <highlighter class="correlation" color="#ffff00"/>
    <highlighter class="does" color="#ffff00"/>
    <highlighter class="reported" color="#00ffff"/>
    <highlighter class="where" color="#ffff00"/>
    <highlighter class="future...research" color="#00ffff"/>
    <highlighter class="have_been_reported" color="#00ffff"/>
    <highlighter class="emerging" color="#ffff00"/>
    <highlighter class="limits" color="#ffff00"/>
    <highlighter class="essential" color="#ccffcc"/>
    <highlighter class="interrelated" color="#00ffff"/>
    <highlighter class="alternatively" color="#00ffff"/>
    <highlighter class="complications" color="#ffcccc"/>
    <highlighter class="data_gap" color="#ffff00"/>
    <highlighter class="noticed" color="#00ffff"/>
    <highlighter class="how" color="#00ffff"/>
    <highlighter class="lacking" color="#ffff00"/>
    <highlighter class="was_shown" color="#00ffff"/>
    <highlighter class="speculative" color="#ffff00"/>
    <highlighter class="call" color="#ccffcc"/>
    <highlighter class="consensus" color="#00ffff"/>
    <highlighter class="unexplained" color="#ffff00"/>
    <highlighter class="affect" color="#ffff00"/>
    <highlighter class="not_yet_settled" color="#ffcccc"/>
    <highlighter class="undetermined" color="#ffff00"/>
    <highlighter class="variations" color="#00ffff"/>
    <highlighter class="theories" color="#ffff00"/>
    <highlighter class="interestingly" color="#00ffff"/>
    <highlighter class="describe" color="#00ffff"/>
    <highlighter class="relations" color="#ffff00"/>
    <highlighter class="linked" color="#ffff00"/>
    <highlighter class="supported" color="#ffff00"/>
    <highlighter class="surely" color="#00ffff"/>
    <highlighter class="correlate" color="#ffff00"/>
    <highlighter class="importantly" color="#ccccff"/>
    <highlighter class="remains" color="#00ffff"/>
    <highlighter class="several_epidemiological_data" color="#ffff00"/>
    <highlighter class="despite" color="#ccccff"/>
    <highlighter class="challenging" color="#ffcccc"/>
    <highlighter class="partially_proven" color="#ffff00"/>
    <highlighter class="while" color="#00ffff"/>
    <highlighter class="debate" color="#ffcccc"/>
    <highlighter class="either" color="#ffff00"/>
    <highlighter class="view" color="#ffff00"/>
    <highlighter class="uncontrolled" color="#00ffff"/>
    <highlighter class="effect" color="#00ffff"/>
    <highlighter class="bias" color="#ffff00"/>
    <highlighter class="need_to_be" color="#ccffcc"/>
    <highlighter class="relatively_few" color="#ffff00"/>
    <highlighter class="in_light_of" color="#00ffff"/>
    <highlighter class="has_to_be" color="#ccffcc"/>
    <highlighter class="scant_evidence" color="#ffff00"/>
    <highlighter class="estimates" color="#00ffff"/>
    <highlighter class="given" color="#00ffff"/>
    <highlighter class="modest_sample_size" color="#ffff00"/>
    <highlighter class="might" color="#ffff00"/>
    <highlighter class="weight" color="#00ffff"/>
    <highlighter class="doubt" color="#ffcccc"/>
    <highlighter class="insufficient" color="#00ffff"/>
    <highlighter class="would_be" color="#ccffcc"/>
    <highlighter class="important" color="#00ffff"/>
    <highlighter class="correlates" color="#00ffff"/>
    <highlighter class="surprising" color="#00ffff"/>
    <highlighter class="alternative_options_controversy" color="#00ffff"/>
    <highlighter class="difficulty" color="#ffcccc"/>
    <highlighter class="recommended" color="#00ffff"/>
    <highlighter class="available_evidence" color="#00ffff"/>
    <highlighter class="involved" color="#ffff00"/>
    <highlighter class="serve" color="#00ffff"/>
    <highlighter class="interrelationships" color="#ffff00"/>
    <highlighter class="attracted_increasing_interest" color="#ffff00"/>
    <highlighter class="remains_elusive" color="#ffff00"/>
    <highlighter class="well_established" color="#00ffff"/>
    <highlighter class="potential" color="#00ffff"/>
    <highlighter class="correlated" color="#00ffff"/>
    <highlighter class="tend" color="#00ffff"/>
    <highlighter class="preliminary_evidence" color="#ffff00"/>
    <highlighter class="existing_evidence" color="#ffff00"/>
    <highlighter class="counterintuitive" color="#ccccff"/>
    <highlighter class="candidate" color="#ffff00"/>
    <highlighter class="prospects" color="#00ffff"/>
    <highlighter class="warranted" color="#ccffcc"/>
    <highlighter class="impossible" color="#ffcccc"/>
    <highlighter class="show" color="#00ffff"/>
    <highlighter class="further_evidence" color="#ffff00"/>
    <highlighter class="conclusion" color="#00ffff"/>
    <highlighter class="why" color="#ffff00"/>
    <highlighter class="interaction" color="#ffff00"/>
    <highlighter class="may_be" color="#ffff00"/>
    <highlighter class="additional_research" color="#ccffcc"/>
    <highlighter class="further" color="#00ffff"/>
    <highlighter class="inadequately_understood" color="#ffff00"/>
    <highlighter class="have_not_been_well_studied" color="#ffff00"/>
    <highlighter class="critical" color="#00ffff"/>
    <highlighter class="impose" color="#ffff00"/>
    <highlighter class="recent_studies" color="#ffff00"/>
    <highlighter class="prudent" color="#ccffcc"/>
    <highlighter class="hence" color="#00ffff"/>
    <highlighter class="surrogate" color="#00ffff"/>
    <highlighter class="supporting" color="#ffff00"/>
    <highlighter class="factor" color="#00ffff"/>
    <highlighter class="these_findings" color="#00ffff"/>
    <highlighter class="enhance" color="#00ffff"/>
    <highlighter class="studies_are_underway" color="#ffff00"/>
    <highlighter class="opposing" color="#ffcccc"/>
    <highlighter class="question_answered_by_this_work" color="#00ffff"/>
    <highlighter class="estimated" color="#00ffff"/>
    <highlighter class="yet" color="#ccccff"/>
    <highlighter class="due_to" color="#00ffff"/>
    <highlighter class="has_been" color="#ffff00"/>
    <highlighter class="target" color="#00ffff"/>
    <highlighter class="more_data_are_needed" color="#ffff00"/>
    <highlighter class="what" color="#ffff00"/>
    <highlighter class="current_evidence" color="#00ffff"/>
    <highlighter class="also_shown" color="#00ffff"/>
    <highlighter class="found_evidence" color="#ffff00"/>
    <highlighter class="this_possibility" color="#ffff00"/>
    <highlighter class="lack_of_rigor" color="#ffff00"/>
    <highlighter class="did_not" color="#00ffff"/>
    <highlighter class="not_only...but_also" color="#00ffff"/>
    <highlighter class="recent_research" color="#ffff00"/>
    <highlighter class="too_crude" color="#ffff00"/>
    <highlighter class="has_shown" color="#00ffff"/>
    <highlighter class="further_work" color="#ccffcc"/>
    <highlighter class="anomaly_curious_finding" color="#ccccff"/>
    <highlighter class="well_documented" color="#ffff00"/>
    <highlighter class="better" color="#00ffff"/>
    <highlighter class="when" color="#00ffff"/>
    <highlighter class="issues" color="#ffcccc"/>
    <highlighter class="when" color="#00ffff"/>
    <highlighter class="scanty_reports" color="#ffff00"/>
    <highlighter class="required" color="#00ffff"/>
    <highlighter class="not...established" color="#00ffff"/>
    <highlighter class="identified" color="#00ffff"/>
    <highlighter class="sought" color="#ff6600"/>
    <highlighter class="premise" color="#ffff00"/>
    <highlighter class="no_one" color="#00ffff"/>
    <highlighter class="future" color="#ccffcc"/>
    <highlighter class="controversial" color="#ffcccc"/>
    <highlighter class="struggling" color="#ffcccc"/>
    <highlighter class="knowledge_gap" color="#ffff00"/>
    <highlighter class="few...options" color="#ffff00"/>
    <highlighter class="not_previously_been_reported" color="#ffff00"/>
    <highlighter class="promising" color="#ffff00"/>
    <highlighter class="previous_study" color="#ffff00"/>
    <highlighter class="future_translational_studies" color="#ccffcc"/>
    <highlighter class="evidence_base" color="#ffff00"/>
    <highlighter class="some_studies" color="#00ffff"/>
    <highlighter class="probability" color="#ffff00"/>
    <highlighter class="conclusions" color="#00ffff"/>
    <highlighter class="gaps_in_current_knowledge" color="#ffff00"/>
    <highlighter class="fairly_consistent" color="#ffff00"/>
    <highlighter class="philosophy" color="#ffff00"/>
    <highlighter class="priority" color="#ccffcc"/>
    <highlighter class="future_options" color="#ccffcc"/>
    <highlighter class="to_determine" color="#00ffff"/>
    <highlighter class="do_not_support" color="#ffcccc"/>
    <highlighter class="affects" color="#00ffff"/>
    <highlighter class="remains...partially" color="#ffff00"/>
    <highlighter class="premise" color="#ffff00"/>
    <highlighter class="burdens" color="#ffcccc"/>
    <highlighter class="requires" color="#00ffff"/>
    <highlighter class="these_findings" color="#00ffff"/>
    <highlighter class="warrants_investigation" color="#ccffcc"/>
    <highlighter class="warrants_further_investigation" color="#ccffcc"/>
    <highlighter class="little_knowledge" color="#ffff00"/>
    <highlighter class="cannot_be" color="#ffcccc"/>
    <highlighter class="further_scientific_research" color="#ccffcc"/>
    <highlighter class="imprecise" color="#ffcccc"/>
    <highlighter class="varied_widely" color="#ffcccc"/>
    <highlighter class="reliability" color="#00ffff"/>
    <highlighter class="differences" color="#00ffff"/>
    <highlighter class="pattern" color="#00ffff"/>
    <highlighter class="remain_to_be_determined" color="#ffff00"/>
    <highlighter class="additional_studies" color="#00ffff"/>
    <highlighter class="confirmed" color="#00ffff"/>
    <highlighter class="unknown" color="#ffff00"/>
    <highlighter class="unknown" color="#ffff00"/>
    <highlighter class="existing_literature" color="#00ffff"/>
    <highlighter class="show" color="#00ffff"/>
    <highlighter class="curious_finding" color="#ccccff"/>
    <highlighter class="probability" color="#ffff00"/>
    <highlighter class="further_investigation" color="#ccffcc"/>
    <highlighter class="principles" color="#00ffff"/>
    <highlighter class="lacks_efficacy" color="#ffff00"/>
    <highlighter class="criticized" color="#ffcccc"/>
    <highlighter class="no_conclusion" color="#ffcccc"/>
    <highlighter class="emerging_research" color="#ffff00"/>
    <highlighter class="no...exist" color="#ffff00"/>
    <highlighter class="to_evaluate" color="#00ffff"/>
    <highlighter class="errors" color="#ffcccc"/>
    <highlighter class="consistent" color="#00ffff"/>
    <highlighter class="additional_studies" color="#00ffff"/>
    <highlighter class="debate" color="#ffcccc"/>
    <highlighter class="heterogeneity" color="#ffcccc"/>
    <highlighter class="was_not" color="#00ffff"/>
    <highlighter class="recommendation" color="#ccffcc"/>
    <highlighter class="criticized" color="#ffcccc"/>
    <highlighter class="determinants" color="#00ffff"/>
    <highlighter class="indicates" color="#ffff00"/>
    <highlighter class="reduce_the_ability_to_make_firm_conclusions" color="#00ffff"/>
    <highlighter class="cause_for_concern" color="#ccffcc"/>
    <highlighter class="easily_confused" color="#ffcccc"/>
    <highlighter class="wide_range" color="#ffcccc"/>
    <highlighter class="indicated" color="#ffff00"/>
    <highlighter class="wondered" color="#ffff00"/>
    <highlighter class="small" color="#00ffff"/>
    <highlighter class="indicator" color="#00ffff"/>
    <highlighter class="have...been" color="#ffff00"/>
    <highlighter class="has_not_been_well_characterized" color="#ffff00"/>
    <highlighter class="recommendations" color="#ccffcc"/>
    <highlighter class="assumptions" color="#00ffff"/>
    <highlighter class="not_well_known" color="#ffff00"/>
    <highlighter class="influence" color="#00ffff"/>
    <highlighter class="therefore" color="#00ffff"/>
    <highlighter class="might" color="#ffff00"/>
    <highlighter class="gap_in_knowledge" color="#ffff00"/>
    <highlighter class="shows" color="#00ffff"/>
    <highlighter class="major" color="#00ffff"/>
    <highlighter class="shown" color="#00ffff"/>
    <highlighter class="little_evidence" color="#ffff00"/>
    <highlighter class="controversies" color="#ffcccc"/>
    <highlighter class="emphasis" color="#ccffcc"/>
    <highlighter class="theoretically" color="#ffff00"/>
    <highlighter class="few" color="#00ffff"/>
    <highlighter class="pointing" color="#00ffff"/>
    <highlighter class="feasible" color="#ffff00"/>
    <highlighter class="remains_limited" color="#ffff00"/>
    <highlighter class="cannot_agree" color="#ffcccc"/>
    <highlighter class="what" color="#ffff00"/>
    <highlighter class="consider" color="#ccffcc"/>
    <highlighter class="recommends" color="#ccffcc"/>
    <highlighter class="potential" color="#00ffff"/>
    <highlighter class="worthy_of_closer_attention" color="#ccffcc"/>
    <highlighter class="connections" color="#00ffff"/>
    <highlighter class="described" color="#00ffff"/>
    <highlighter class="speculation" color="#ffff00"/>
    <highlighter class="contradicting" color="#ffcccc"/>
    <highlighter class="crisis" color="#ccffcc"/>
    <highlighter class="here...investigated" color="#ff6600"/>
    <highlighter class="could_not_determine" color="#ffff00"/>
    <highlighter class="center_of_attention" color="#ffff00"/>
    <highlighter class="less_is_known" color="#ffff00"/>
    <highlighter class="insufficient" color="#00ffff"/>
    <highlighter class="has_been" color="#ffff00"/>
    <highlighter class="alternative_options_controversy" color="#00ffff"/>
    <highlighter class="important" color="#00ffff"/>
    <highlighter class="effects" color="#00ffff"/>
    <highlighter class="growing_agreement" color="#ffff00"/>
    <highlighter class="correlate" color="#ffff00"/>
    <highlighter class="insufficient_evidence" color="#ffff00"/>
    <highlighter class="effect" color="#00ffff"/>
    <highlighter class="hypothesised" color="#ffff00"/>
    <highlighter class="has...been" color="#00ffff"/>
    <highlighter class="increased_attention" color="#ffff00"/>
    <highlighter class="limitation" color="#ffff00"/>
    <highlighter class="alternately" color="#00ffff"/>
    <highlighter class="recent_studies" color="#ffff00"/>
    <highlighter class="research...limited" color="#ffff00"/>
    <highlighter class="critical" color="#00ffff"/>
    <highlighter class="research_gaps" color="#ffff00"/>
    <highlighter class="increasingly_recognised" color="#ffff00"/>
    <highlighter class="unexpected" color="#ccccff"/>
    <highlighter class="crucial" color="#ccffcc"/>
    <highlighter class="reveals" color="#ffff00"/>
    <highlighter class="contribute" color="#00ffff"/>
    <highlighter class="investigations" color="#ccffcc"/>
    <highlighter class="why" color="#ffff00"/>
    <highlighter class="affecting" color="#00ffff"/>
    <highlighter class="explicit_question" color="#ffff00"/>
    <highlighter class="associated...or" color="#ffff00"/>
    <highlighter class="point" color="#ffff00"/>
    <highlighter class="interactions" color="#ffff00"/>
    <highlighter class="in_summary" color="#00ffff"/>
    <highlighter class="tend" color="#00ffff"/>
    <highlighter class="highlight" color="#00ffff"/>
    <highlighter class="candidate" color="#ffff00"/>
    <highlighter class="similar" color="#00ffff"/>
    <highlighter class="0_important_consideration" color="#00ffff"/>
    <highlighter class="future_trials" color="#ccffcc"/>
    <highlighter class="dilemmas" color="#ffcccc"/>
    <highlighter class="requirements" color="#00ffff"/>
    <highlighter class="studies_are_required_to_confirm" color="#ccffcc"/>
    <highlighter class="warrant_an_investigation" color="#ccffcc"/>
    <highlighter class="probable_understanding" color="#ffff00"/>
    <highlighter class="alternative" color="#ffff00"/>
    <highlighter class="alternative_hypotheses" color="#ffff00"/>
    <highlighter class="has_been_shown" color="#00ffff"/>
    <highlighter class="differ" color="#ffcccc"/>
    <highlighter class="conclusion" color="#00ffff"/>
    <highlighter class="recommended" color="#00ffff"/>
    <highlighter class="still_evolving" color="#ffff00"/>
    <highlighter class="far_from_understanding" color="#ffff00"/>
    <highlighter class="Barriers" color="#ffcccc"/>
    <highlighter class="emerging_knowledge" color="#ffff00"/>
    <highlighter class="interaction" color="#ffff00"/>
    <highlighter class="research_evidence" color="#ffff00"/>
    <highlighter class="perhaps" color="#ffff00"/>
    <highlighter class="attention" color="#ccffcc"/>
    <highlighter class="suggestions" color="#ccffcc"/>
    <highlighter class="further" color="#00ffff"/>
    <highlighter class="simply" color="#00ffff"/>
    <highlighter class="remains_under-studied" color="#ffff00"/>
    <highlighter class="evidence_is_accumulating" color="#ffff00"/>
    <highlighter class="data_are_limited" color="#ffff00"/>
    <highlighter class="mostly" color="#ffff00"/>
    <highlighter class="call_to_act" color="#ccffcc"/>
    <highlighter class="open_question" color="#ffff00"/>
    <highlighter class="vary" color="#00ffff"/>
    <highlighter class="likely_be" color="#ffff00"/>
    <highlighter class="conversely" color="#00ffff"/>
    <highlighter class="was_shown" color="#00ffff"/>
    <highlighter class="warrants_research" color="#ccffcc"/>
    <highlighter class="seem_to_be" color="#ccccff"/>
    <highlighter class="observed" color="#00ffff"/>
    <highlighter class="future_prediction" color="#ccffcc"/>
    <highlighter class="have_reported" color="#00ffff"/>
    <highlighter class="interrelationship" color="#ffff00"/>
    <highlighter class="complex" color="#ffcccc"/>
    <highlighter class="not_possible" color="#00ffff"/>
    <highlighter class="assumption" color="#ffcccc"/>
    <highlighter class="shed_light" color="#ffff00"/>
    <highlighter class="evidence...is_scarce" color="#ffff00"/>
    <highlighter class="investigated" color="#00ffff"/>
    <highlighter class="no...is_known" color="#ffff00"/>
    <highlighter class="limitations" color="#ffff00"/>
    <highlighter class="incomplete_evidence" color="#ffff00"/>
    <highlighter class="disparities" color="#ffcccc"/>
    <highlighter class="remains_a_common_occurrence" color="#ffff00"/>
    <highlighter class="need_for_more_trials" color="#ccffcc"/>
    <highlighter class="public_health" color="#00ffff"/>
    <highlighter class="strategies" color="#00ffff"/>
    <highlighter class="impact" color="#ffff00"/>
    <highlighter class="opportunity" color="#ccffcc"/>
    <highlighter class="in_contrast" color="#00ffff"/>
    <highlighter class="probable_understanding" color="#ffff00"/>
    <highlighter class="not...adequately_explored" color="#ffff00"/>
    <highlighter class="accurately" color="#00ffff"/>
    <highlighter class="future_studies" color="#ccffcc"/>
    <highlighter class="mixed" color="#ffcccc"/>
    <highlighter class="unorthodox" color="#ffcccc"/>
    <highlighter class="extend" color="#00ffff"/>
    <highlighter class="warrant_additional_discussion" color="#ccffcc"/>
    <highlighter class="as" color="#00ffff"/>
    <highlighter class="found_to_be" color="#00ffff"/>
    <highlighter class="of_note" color="#00ffff"/>
    <highlighter class="aim_to" color="#00ffff"/>
    <highlighter class="interpretation" color="#ffff00"/>
    <highlighter class="consideration" color="#ccffcc"/>
    <highlighter class="needs_to_be_determined" color="#ccffcc"/>
    <highlighter class="could...not" color="#00ffff"/>
    <highlighter class="have_not_been_identified" color="#ffff00"/>
    <highlighter class="relationship" color="#00ffff"/>
    <highlighter class="several_studies" color="#ffff00"/>
    <highlighter class="not_specifically_designed_to" color="#ffff00"/>
    <highlighter class="affect" color="#ffff00"/>
    <highlighter class="consequently" color="#00ffff"/>
    <highlighter class="Epistemics" color="#00ffff"/>
    <highlighter class="limited_number" color="#ffff00"/>
    <highlighter class="to_investigate" color="#00ffff"/>
    <highlighter class="remains_relatively_unexplored" color="#ffff00"/>
    <highlighter class="approach_that_considers" color="#ccffcc"/>
    <highlighter class="confirm_findings" color="#ffff00"/>
    <highlighter class="how" color="#00ffff"/>
    <highlighter class="interestingly" color="#00ffff"/>
    <highlighter class="necessary" color="#00ffff"/>
    <highlighter class="calls_into_question" color="#ffcccc"/>
    <highlighter class="unlike" color="#00ffff"/>
    <highlighter class="more_research" color="#00ffff"/>
    <highlighter class="indicate" color="#00ffff"/>
    <highlighter class="so-called" color="#00ffff"/>
    <highlighter class="it_is_possible" color="#ffff00"/>
    <highlighter class="watchwords" color="#ffff00"/>
    <highlighter class="further_study" color="#ccffcc"/>
    <highlighter class="ongoing_research" color="#ffff00"/>
    <highlighter class="but_only" color="#00ffff"/>
    <highlighter class="unable_to" color="#00ffff"/>
    <highlighter class="preliminary_stage" color="#ffff00"/>
    <highlighter class="risk_factors" color="#00ffff"/>
    <highlighter class="predictive" color="#00ffff"/>
    <highlighter class="confirm" color="#ffff00"/>
    <highlighter class="this_study" color="#ff6600"/>
    <highlighter class="partly" color="#ffff00"/>
    <highlighter class="possible" color="#ffff00"/>
    <highlighter class="not_known" color="#ffff00"/>
    <highlighter class="supports" color="#ffff00"/>
    <highlighter class="difficulties" color="#ffcccc"/>
    <highlighter class="most_studies...but" color="#ffcccc"/>
    <highlighter class="insufficiency" color="#00ffff"/>
    <highlighter class="complicated" color="#ffcccc"/>
    <highlighter class="would_be_expected" color="#ccffcc"/>
    <highlighter class="notion" color="#ffff00"/>
    <highlighter class="associations" color="#ffff00"/>
    <highlighter class="validity" color="#00ffff"/>
    <highlighter class="represent" color="#00ffff"/>
    <highlighter class="misclassification" color="#ffcccc"/>
    <highlighter class="essential" color="#ccffcc"/>
    <highlighter class="reported" color="#00ffff"/>
    <highlighter class="based_on" color="#00ffff"/>
    <highlighter class="important_consideration" color="#00ffff"/>
    <highlighter class="findings" color="#00ffff"/>
    <highlighter class="sometimes" color="#00ffff"/>
    <highlighter class="remain_to_be_defined" color="#ffff00"/>
    <highlighter class="questions" color="#ffff00"/>
    <highlighter class="presumed" color="#ffff00"/>
    <highlighter class="promise" color="#ffff00"/>
    <highlighter class="recommendations" color="#ccffcc"/>
    <highlighter class="attracted_attention" color="#ffff00"/>
    <highlighter class="underestimation" color="#00ffff"/>
    <highlighter class="small" color="#00ffff"/>
    <highlighter class="remain_limited" color="#ffff00"/>
    <highlighter class="to_identify" color="#00ffff"/>
    <highlighter class="if...or...or" color="#00ffff"/>
    <highlighter class="rare" color="#ffff00"/>
    <highlighter class="on_the_basis_of" color="#00ffff"/>
    <highlighter class="additional_hypotheses" color="#ffff00"/>
    <highlighter class="at_least" color="#ffff00"/>
    <highlighter class="generally_thought" color="#ffff00"/>
    <highlighter class="insufficient...information" color="#ffff00"/>
    <highlighter class="possibly" color="#ffff00"/>
    <highlighter class="which" color="#ffff00"/>
    <highlighter class="needs" color="#ccffcc"/>
    <highlighter class="on_the_other_hand" color="#00ffff"/>
    <highlighter class="appeared_to" color="#ccccff"/>
    <highlighter class="a_good_understanding" color="#ffff00"/>
    <highlighter class="inadequately" color="#00ffff"/>
    <highlighter class="proposed" color="#ffff00"/>
    <highlighter class="remained" color="#00ffff"/>
    <highlighter class="only_few_cases" color="#ffff00"/>
    <highlighter class="more_comprehensive" color="#00ffff"/>
    <highlighter class="effects" color="#00ffff"/>
    <highlighter class="not_well_understood" color="#ffff00"/>
    <highlighter class="subsequent_studies" color="#ffff00"/>
    <highlighter class="has_not_been_widely_studied" color="#ffff00"/>
    <highlighter class="countervailing" color="#ffcccc"/>
    <highlighter class="little_attention" color="#ffff00"/>
    <highlighter class="in_keeping_with" color="#00ffff"/>
    <highlighter class="contradictory" color="#ffcccc"/>
    <highlighter class="subject_of_numerous_studies" color="#ffcccc"/>
    <highlighter class="another_study" color="#00ffff"/>
    <highlighter class="affecting" color="#00ffff"/>
    <highlighter class="further...studies" color="#00ffff"/>
    <highlighter class="varies" color="#ffcccc"/>
    <highlighter class="highlight" color="#00ffff"/>
    <highlighter class="should_be" color="#ccffcc"/>
    <highlighter class="feasible" color="#ffff00"/>
    <highlighter class="research_questions" color="#ffff00"/>
    <highlighter class="data_is_lacking" color="#ffff00"/>
    <highlighter class="however" color="#00ffff"/>
    <highlighter class="some" color="#00ffff"/>
    <highlighter class="additional_research_is_needed" color="#ccffcc"/>
    <highlighter class="identifying" color="#00ffff"/>
    <highlighter class="thought_to" color="#ffff00"/>
    <highlighter class="objectives" color="#ff6600"/>
    <highlighter class="rather" color="#ffcccc"/>
    <highlighter class="importance" color="#ccffcc"/>
    <highlighter class="some...however" color="#ffff00"/>
    <highlighter class="several_explanations" color="#ffff00"/>
    <highlighter class="no...available" color="#ffff00"/>
    <highlighter class="according_to" color="#00ffff"/>
    <highlighter class="explained" color="#00ffff"/>
    <highlighter class="primarily" color="#00ffff"/>
    <highlighter class="burden" color="#00ffff"/>
    <highlighter class="recommend" color="#ccffcc"/>
    <highlighter class="poorly_understood" color="#ffff00"/>
    <highlighter class="perhaps" color="#ffff00"/>
    <highlighter class="related" color="#00ffff"/>
    <highlighter class="number_of" color="#00ffff"/>
    <highlighter class="additional_studies_are_needed" color="#ccffcc"/>
    <highlighter class="argued" color="#ffff00"/>
    <highlighter class="determinant" color="#00ffff"/>
    <highlighter class="contrary" color="#ffcccc"/>
    <highlighter class="has_not_been_established_so_far" color="#ffff00"/>
    <highlighter class="tabooed" color="#ffcccc"/>
    <highlighter class="influences" color="#ffff00"/>
    <highlighter class="affects" color="#00ffff"/>
    <highlighter class="obviously" color="#00ffff"/>
    <highlighter class="this_investigation" color="#ff6600"/>
    <highlighter class="two_major_hypotheses" color="#ffff00"/>
    <highlighter class="concerns" color="#ffcccc"/>
    <highlighter class="many...studies" color="#00ffff"/>
    <highlighter class="set_a_precedent" color="#ffff00"/>
    <highlighter class="considerations" color="#ccffcc"/>
    <highlighter class="interventions_are_needed" color="#ccffcc"/>
    <highlighter class="influenced" color="#00ffff"/>
    <highlighter class="unresolved_issues" color="#ffcccc"/>
    <highlighter class="or" color="#00ffff"/>
    <highlighter class="approximately" color="#00ffff"/>
    <highlighter class="although" color="#ccccff"/>
    <highlighter class="lack_of" color="#ffff00"/>
    <highlighter class="have...been" color="#ffff00"/>
    <highlighter class="be_examined" color="#ffff00"/>
    <highlighter class="recommends" color="#ccffcc"/>
    <highlighter class="unrecognized" color="#ffff00"/>
    <highlighter class="in_agreement" color="#00ffff"/>
    <highlighter class="showing" color="#00ffff"/>
    <highlighter class="explain" color="#00ffff"/>
    <highlighter class="anomaly_curious_finding" color="#ccccff"/>
    <highlighter class="revealed" color="#ffff00"/>
    <highlighter class="hypothesized" color="#ffff00"/>
    <highlighter class="usually" color="#ffff00"/>
    <highlighter class="confounders" color="#00ffff"/>
    <highlighter class="recommendation" color="#ccffcc"/>
    <highlighter class="need...data" color="#ccffcc"/>
    <highlighter class="interacts" color="#ffff00"/>
    <highlighter class="remains_unclear" color="#ffff00"/>
    <highlighter class="relationships" color="#ffff00"/>
    <highlighter class="remain_scarce" color="#ffff00"/>
    <highlighter class="appeared" color="#ccccff"/>
    <highlighter class="warrants" color="#ccffcc"/>
    <highlighter class="uncritically" color="#ffcccc"/>
    <highlighter class="impaired" color="#00ffff"/>
    <highlighter class="some_studies" color="#00ffff"/>
    <highlighter class="is_known" color="#00ffff"/>
    <highlighter class="revealed" color="#ffff00"/>
    <highlighter class="insight" color="#ffff00"/>
    <highlighter class="majority" color="#00ffff"/>
    <highlighter class="usually" color="#ffff00"/>
    <highlighter class="whereas" color="#00ffff"/>
    <highlighter class="influencing" color="#00ffff"/>
    <highlighter class="if" color="#ffff00"/>
    <highlighter class="has_been_demonstrated" color="#ffff00"/>
    <highlighter class="validation" color="#ffff00"/>
    <highlighter class="Future_Opportunities" color="#ccffcc"/>
    <highlighter class="crucially" color="#00ffff"/>
    <highlighter class="first" color="#00ffff"/>
    <highlighter class="conflicted" color="#ffcccc"/>
    <highlighter class="likely" color="#ffff00"/>
    <highlighter class="number_of_studies" color="#ffff00"/>
    <highlighter class="issue" color="#ffcccc"/>
    <highlighter class="not_explained" color="#ffff00"/>
    <highlighter class="suspected" color="#00ffff"/>
    <highlighter class="present_study" color="#ff6600"/>
    <highlighter class="need...evidence" color="#ffff00"/>
    <highlighter class="likely" color="#ffff00"/>
    <highlighter class="is" color="#ffff00"/>
    <highlighter class="previous_study" color="#ffff00"/>
    <highlighter class="little_is_known" color="#ffff00"/>
    <highlighter class="aimed" color="#ff6600"/>
    <highlighter class="problem" color="#ffcccc"/>
    <highlighter class="could_be" color="#ffff00"/>
    <highlighter class="no...has_been_conducted" color="#ffff00"/>
    <highlighter class="confirm_previous_findings" color="#ffff00"/>
    <highlighter class="to...examine" color="#00ffff"/>
    <highlighter class="accompanied" color="#ffff00"/>
    <highlighter class="interest" color="#ccccff"/>
    <highlighter class="if" color="#ffff00"/>
    <highlighter class="lead_to" color="#00ffff"/>
    <highlighter class="still_being_elucidated" color="#ffff00"/>
    <highlighter class="mediate" color="#00ffff"/>
    <highlighter class="not...conclusive" color="#ffcccc"/>
    <highlighter class="information...is_scarce" color="#ffff00"/>
    <highlighter class="some" color="#00ffff"/>
    <highlighter class="focuses" color="#00ffff"/>
    <highlighter class="could...and_or" color="#ffff00"/>
    <highlighter class="targets" color="#00ffff"/>
    <highlighter class="targets" color="#00ffff"/>
    <highlighter class="has_been_found" color="#ffff00"/>
    <highlighter class="would_be" color="#ccffcc"/>
    <highlighter class="known" color="#00ffff"/>
    <highlighter class="unanticipated" color="#ccccff"/>
    <highlighter class="urgent" color="#ccffcc"/>
    <highlighter class="belief" color="#ffff00"/>
    <highlighter class="clues" color="#ffff00"/>
    <highlighter class="explosion_of_knowledge" color="#ffff00"/>
    <highlighter class="in_part" color="#00ffff"/>
    <highlighter class="paradoxical" color="#ffcccc"/>
    <highlighter class="suggest" color="#00ffff"/>
    <highlighter class="urgent_call_to_action" color="#ccffcc"/>
    <highlighter class="may" color="#ffff00"/>
    <highlighter class="has_seen" color="#ffff00"/>
    <highlighter class="seemed" color="#ccccff"/>
    <highlighter class="could" color="#ffff00"/>
    <highlighter class="suggestion" color="#00ffff"/>
    <highlighter class="lacks" color="#ffff00"/>
    <highlighter class="not...clear" color="#ffff00"/>
    <highlighter class="myths" color="#ffcccc"/>
    <highlighter class="defining" color="#ffff00"/>
    <highlighter class="Levels_Of_Evidence" color="#ffff00"/>
    <highlighter class="has_recently_been" color="#ffff00"/>
    <highlighter class="generally" color="#00ffff"/>
    <highlighter class="prospect" color="#ffff00"/>
    <highlighter class="need_for_validation_studies" color="#ccffcc"/>
    <highlighter class="future_investigations" color="#ccffcc"/>
    <highlighter class="may" color="#ffff00"/>
    <highlighter class="important_consideration" color="#00ffff"/>
    <highlighter class="emerges" color="#ffff00"/>
    <highlighter class="have_been_shown" color="#00ffff"/>
    <highlighter class="to_evaluate" color="#00ffff"/>
    <highlighter class="comparable" color="#00ffff"/>
    <highlighter class="linkages" color="#ffff00"/>
    <highlighter class="0_claim" color="#ffff00"/>
    <highlighter class="underestimation" color="#00ffff"/>
    <highlighter class="not_know" color="#ffff00"/>
    <highlighter class="concerned" color="#00ffff"/>
    <highlighter class="presumably" color="#ffff00"/>
    <highlighter class="lack_of...data" color="#ffff00"/>
    <highlighter class="serve" color="#00ffff"/>
    <highlighter class="randomized_controlled_trials_are_needed" color="#ccffcc"/>
    <highlighter class="no_conclusive_evidence" color="#ffff00"/>
    <highlighter class="while" color="#00ffff"/>
    <highlighter class="no_known" color="#ffff00"/>
    <highlighter class="heterogeneous" color="#ffcccc"/>
    <highlighter class="is_thought" color="#ffff00"/>
    <highlighter class="as_expected" color="#00ffff"/>
    <highlighter class="confused" color="#ffcccc"/>
    <highlighter class="not_univocal" color="#ffcccc"/>
    <highlighter class="suggests" color="#ffff00"/>
    <highlighter class="corresponded" color="#ffff00"/>
    <highlighter class="experimental_evidence" color="#ffff00"/>
    <highlighter class="lack_of" color="#ffff00"/>
    <highlighter class="documented" color="#00ffff"/>
    <highlighter class="than" color="#00ffff"/>
    <highlighter class="startling_finding" color="#ccccff"/>
    <highlighter class="not_yet" color="#00ffff"/>
    <highlighter class="longitudinal_studies...are_needed" color="#ccffcc"/>
    <highlighter class="different" color="#00ffff"/>
    <highlighter class="have_shown" color="#ffff00"/>
    <highlighter class="regardless_of" color="#00ffff"/>
    <highlighter class="not_previously_been" color="#ffff00"/>
    <highlighter class="continuing_efforts" color="#ccffcc"/>
    <highlighter class="has_not_been_reported" color="#ffff00"/>
    <highlighter class="difficult" color="#ffcccc"/>
    <highlighter class="question_answered_by_this_work" color="#00ffff"/>
    <highlighter class="our_findings" color="#00ffff"/>
    <highlighter class="relevant" color="#00ffff"/>
    <highlighter class="under-studied" color="#ffff00"/>
    <highlighter class="more_comprehensive" color="#00ffff"/>
    <highlighter class="appeared_to" color="#ccccff"/>
    <highlighter class="stronger_evidence_base" color="#ffff00"/>
    <highlighter class="suggestive" color="#ffff00"/>
    <highlighter class="true" color="#00ffff"/>
    <highlighter class="principles" color="#00ffff"/>
    <highlighter class="first_data" color="#ffff00"/>
    <highlighter class="nonetheless" color="#00ffff"/>
    <highlighter class="further_study" color="#ccffcc"/>
    <highlighter class="contrary" color="#ffcccc"/>
    <highlighter class="errors" color="#ffcccc"/>
    <highlighter class="since" color="#00ffff"/>
    <highlighter class="problems" color="#ffcccc"/>
    <highlighter class="other_studies" color="#00ffff"/>
    <highlighter class="rather" color="#ffcccc"/>
    <highlighter class="increasing...evidence" color="#ffff00"/>
    <highlighter class="appears" color="#ccccff"/>
    <highlighter class="mixed" color="#ffcccc"/>
    <highlighter class="allow" color="#00ffff"/>
    <highlighter class="no...trials" color="#00ffff"/>
    <highlighter class="uncommon" color="#ffff00"/>
    <highlighter class="considerable" color="#00ffff"/>
    <highlighter class="dont_know" color="#ffff00"/>
    <highlighter class="our_study" color="#00ffff"/>
    <highlighter class="also_shown" color="#00ffff"/>
    <highlighter class="did_not" color="#00ffff"/>
    <highlighter class="larger...studies" color="#00ffff"/>
    <highlighter class="lack_of_evidence" color="#ffff00"/>
    <highlighter class="viable" color="#ffff00"/>
    <highlighter class="cannot_be" color="#ffcccc"/>
    <highlighter class="as_in" color="#00ffff"/>
    <highlighter class="future_work" color="#00ffff"/>
    <highlighter class="or" color="#00ffff"/>
    <highlighter class="problematic" color="#ffcccc"/>
    <highlighter class="questioned" color="#ffcccc"/>
    <highlighter class="considerably" color="#00ffff"/>
    <highlighter class="interesting" color="#ccccff"/>
    <highlighter class="may_be" color="#ffff00"/>
    <highlighter class="sought" color="#ff6600"/>
    <highlighter class="not_been_studied" color="#ffff00"/>
    <highlighter class="difficult_task" color="#ffcccc"/>
    <highlighter class="whilst" color="#00ffff"/>
    <highlighter class="importantly" color="#ccccff"/>
    <highlighter class="is_considered" color="#00ffff"/>
    <highlighter class="concerning" color="#ffcccc"/>
    <highlighter class="whether...or" color="#ffff00"/>
    <highlighter class="perspectives" color="#ffff00"/>
    <highlighter class="evident" color="#00ffff"/>
    <highlighter class="implicated" color="#ffff00"/>
    <highlighter class="0_unexpected_observation" color="#ccccff"/>
    <highlighter class="need_to_develop...strategies" color="#ccffcc"/>
    <highlighter class="emphasize" color="#00ffff"/>
    <highlighter class="studies...are_warranted" color="#ccffcc"/>
    <highlighter class="vary" color="#00ffff"/>
    <highlighter class="observed" color="#00ffff"/>
    <highlighter class="objective" color="#ff6600"/>
    <highlighter class="to_the_best_of_our_knowledge" color="#00ffff"/>
    <highlighter class="reflect" color="#00ffff"/>
    <highlighter class="contribution" color="#00ffff"/>
    <highlighter class="most_likely" color="#ffff00"/>
    <highlighter class="encouraged" color="#00ffff"/>
    <highlighter class="but_others" color="#ffcccc"/>
    <highlighter class="refutes" color="#ffcccc"/>
    <highlighter class="raises" color="#00ffff"/>
    <highlighter class="no_clear_evidence" color="#ffff00"/>
    <highlighter class="estimate" color="#00ffff"/>
    <highlighter class="could_not" color="#ffcccc"/>
    <highlighter class="goals" color="#00ffff"/>
    <highlighter class="proposal" color="#ffff00"/>
    <highlighter class="not_been_studied" color="#ffff00"/>
    <highlighter class="protective" color="#00ffff"/>
    <highlighter class="inadequate" color="#00ffff"/>
    <highlighter class="notably" color="#ccccff"/>
    <highlighter class="eludes" color="#ffff00"/>
    <highlighter class="would" color="#ccffcc"/>
    <highlighter class="larger_studies" color="#ccffcc"/>
    <highlighter class="evidence...is_scarce" color="#ffff00"/>
    <highlighter class="link" color="#ffff00"/>
    <highlighter class="future_research" color="#00ffff"/>
    <highlighter class="have_reported" color="#00ffff"/>
    <highlighter class="impact" color="#ffff00"/>
    <highlighter class="unique" color="#00ffff"/>
    <highlighter class="limited_number_of_studies" color="#ffff00"/>
    <highlighter class="consistently" color="#00ffff"/>
    <highlighter class="however" color="#00ffff"/>
    <highlighter class="here" color="#ff6600"/>
    <highlighter class="interpreted" color="#00ffff"/>
    <highlighter class="few...studies" color="#ffff00"/>
    <highlighter class="nevertheless" color="#00ffff"/>
    <highlighter class="examine" color="#00ffff"/>
    <highlighter class="concluded" color="#00ffff"/>
    <highlighter class="not_observed" color="#00ffff"/>
    <highlighter class="advisable" color="#00ffff"/>
    <highlighter class="not_known" color="#ffff00"/>
    <highlighter class="association" color="#00ffff"/>
    <highlighter class="believe" color="#ffff00"/>
    <highlighter class="remains_to_be_elucidated" color="#ffff00"/>
    <highlighter class="but_not" color="#00ffff"/>
    <highlighter class="extended" color="#00ffff"/>
    <highlighter class="seen" color="#00ffff"/>
    <highlighter class="seem" color="#ccccff"/>
    <highlighter class="study_and_address" color="#ccffcc"/>
    <highlighter class="future_studies" color="#ccffcc"/>
    <highlighter class="interpretation" color="#ffff00"/>
    <highlighter class="roles" color="#00ffff"/>
    <highlighter class="variety" color="#ffcccc"/>
    <highlighter class="difficulties" color="#ffcccc"/>
    <highlighter class="supports" color="#ffff00"/>
    <highlighter class="have_not_been_studied" color="#ffff00"/>
    <highlighter class="examined" color="#00ffff"/>
    <highlighter class="relationship" color="#00ffff"/>
    <highlighter class="caution" color="#ffff00"/>
    <highlighter class="alternative_approaches" color="#ffff00"/>
    <highlighter class="preferred" color="#00ffff"/>
    <highlighter class="appears_to_be" color="#ccccff"/>
    <highlighter class="no_studies" color="#ffff00"/>
    <highlighter class="evidence_to_support" color="#ffff00"/>
    <highlighter class="though" color="#ccccff"/>
    <highlighter class="associates" color="#ffff00"/>
    <highlighter class="necessary" color="#00ffff"/>
    <highlighter class="rarer" color="#ffff00"/>
    <highlighter class="strategies" color="#00ffff"/>
    <highlighter class="thus" color="#00ffff"/>
    <highlighter class="but_only" color="#00ffff"/>
    <highlighter class="speculate" color="#ffff00"/>
    <highlighter class="appeared_to_be" color="#ccccff"/>
    <highlighter class="to_investigate" color="#00ffff"/>
    <highlighter class="confirm" color="#ffff00"/>
    <highlighter class="connected" color="#ffff00"/>
    <highlighter class="appear" color="#ccccff"/>
    <highlighter class="this_study" color="#ff6600"/>
    <highlighter class="new_research" color="#00ffff"/>
    <highlighter class="replication_studies_are_needed" color="#ccffcc"/>
    <highlighter class="showed" color="#00ffff"/>
    <highlighter class="associated" color="#00ffff"/>
    <highlighter class="lack_of_information" color="#ffff00"/>
    <highlighter class="remain_variable" color="#ffcccc"/>
    <highlighter class="lack_answers" color="#ffff00"/>
    <highlighter class="need_for_further_research" color="#ccffcc"/>
    <highlighter class="partially" color="#ffff00"/>
    <highlighter class="have_shown" color="#ffff00"/>
    <highlighter class="but" color="#00ffff"/>
    <highlighter class="plausibility" color="#ffff00"/>
    <highlighter class="closer_scrutiny" color="#ffff00"/>
    <highlighter class="remarkably" color="#ccccff"/>
    <highlighter class="has_not_occurred" color="#ffcccc"/>
    <highlighter class="to_our_knowledge" color="#00ffff"/>
    <highlighter class="reasonable" color="#00ffff"/>
    <highlighter class="further_studies" color="#ccffcc"/>
    <highlighter class="wished" color="#ff6600"/>
    <highlighter class="has_been_lacking" color="#ffff00"/>
    <highlighter class="new_research_opportunities" color="#ccffcc"/>
    <highlighter class="subject_scope" color="#00ffff"/>
    <highlighter class="more...studies" color="#00ffff"/>
    <highlighter class="advocate" color="#ccffcc"/>
    <highlighter class="to_assess" color="#00ffff"/>
    <highlighter class="has_recently_been" color="#ffff00"/>
    <highlighter class="mainly" color="#ffff00"/>
    <highlighter class="gaps_in_our_knowledge" color="#ffff00"/>
    <highlighter class="conflicting" color="#ffcccc"/>
    <highlighter class="many_studies" color="#ffff00"/>
    <highlighter class="lack_of_knowledge" color="#ffff00"/>
    <highlighter class="opportunities_for_future_research" color="#ccffcc"/>
    <highlighter class="unusual" color="#ffff00"/>
    <highlighter class="future_intervention" color="#00ffff"/>
    <highlighter class="recent...study" color="#00ffff"/>
    <highlighter class="will" color="#00ffff"/>
    <highlighter class="studies...are_needed" color="#ccffcc"/>
    <highlighter class="generally" color="#00ffff"/>
    <highlighter class="beliefs" color="#ffff00"/>
    <highlighter class="largely_driven_by" color="#00ffff"/>
    <highlighter class="discord" color="#ffcccc"/>
    <highlighter class="incompletely" color="#ffff00"/>
    <highlighter class="current_research_provides_evidence" color="#ffff00"/>
    <highlighter class="obscure" color="#ffff00"/>
    <highlighter class="in_order_to" color="#00ffff"/>
    <highlighter class="failure" color="#ffff00"/>
    <highlighter class="superficial_relationship" color="#ffff00"/>
    <highlighter class="not_been_examined" color="#ffff00"/>
    <highlighter class="whether...if" color="#ffff00"/>
    <highlighter class="know" color="#00ffff"/>
    <highlighter class="designed_to" color="#ff6600"/>
    <highlighter class="vital" color="#ccffcc"/>
    <highlighter class="suggesting" color="#00ffff"/>
    <highlighter class="support" color="#00ffff"/>
    <highlighter class="conflict" color="#ffcccc"/>
    <highlighter class="allow" color="#00ffff"/>
    <highlighter class="assessed" color="#00ffff"/>
    <highlighter class="reasons" color="#00ffff"/>
    <highlighter class="needed" color="#00ffff"/>
    <highlighter class="idea" color="#ffff00"/>
    <highlighter class="must...be" color="#ccffcc"/>
    <highlighter class="error" color="#ffcccc"/>
    <highlighter class="has_been_found" color="#ffff00"/>
    <highlighter class="discrepancies" color="#ffcccc"/>
    <highlighter class="interest" color="#ccccff"/>
    <highlighter class="problem_complication" color="#00ffff"/>
    <highlighter class="likelihood" color="#ffff00"/>
    <highlighter class="similarity" color="#00ffff"/>
    <highlighter class="gap" color="#ffff00"/>
    <highlighter class="emphasize" color="#00ffff"/>
    <highlighter class="potentially" color="#00ffff"/>
    <highlighter class="not_been_described" color="#ffff00"/>
    <highlighter class="previous" color="#00ffff"/>
    <highlighter class="modest_evidence" color="#ffff00"/>
    <highlighter class="suggested" color="#ffff00"/>
    <highlighter class="recently" color="#ffff00"/>
    <highlighter class="can" color="#00ffff"/>
    <highlighter class="little_support" color="#ffff00"/>
    <highlighter class="remain_unclear" color="#ffff00"/>
    <highlighter class="concerning" color="#ffcccc"/>
    <highlighter class="difficult_task" color="#ffcccc"/>
    <highlighter class="foreseen" color="#ccffcc"/>
    <highlighter class="accounts_for" color="#00ffff"/>
    <highlighter class="out_of_reach" color="#ffff00"/>
    <highlighter class="few_studies" color="#00ffff"/>
    <highlighter class="unclear" color="#ffff00"/>
    <highlighter class="inter-relationships" color="#ffff00"/>
    <highlighter class="growing_evidence" color="#ffff00"/>
    <highlighter class="the_need" color="#ffff00"/>
    <highlighter class="seemed_to_be" color="#ccccff"/>
    <highlighter class="suggestively" color="#ffff00"/>
    <highlighter class="previous...studies" color="#ffff00"/>
    <highlighter class="only" color="#00ffff"/>
    <highlighter class="should" color="#ccffcc"/>
    <highlighter class="disconnect" color="#ffcccc"/>
    <highlighter class="the_current_study" color="#00ffff"/>
    <highlighter class="need_more_information" color="#ffff00"/>
    <highlighter class="trend" color="#00ffff"/>
    <highlighter class="claimed" color="#ffff00"/>
    <highlighter class="the_current_study" color="#00ffff"/>
    <highlighter class="not_specifically" color="#00ffff"/>
    <highlighter class="no...studies" color="#00ffff"/>
    <highlighter class="none" color="#ffff00"/>
    <highlighter class="relation" color="#00ffff"/>
    <highlighter class="explain" color="#00ffff"/>
    <highlighter class="whether...compared" color="#ffff00"/>
    <highlighter class="reliable" color="#00ffff"/>
    <highlighter class="relate" color="#ffff00"/>
    <highlighter class="problem" color="#ffcccc"/>
    <highlighter class="variably" color="#ffcccc"/>
    <highlighter class="scant" color="#00ffff"/>
    <highlighter class="leading_cause" color="#00ffff"/>
    <highlighter class="safety" color="#00ffff"/>
    <highlighter class="justify" color="#00ffff"/>
    <highlighter class="has_not_been_adequately_investigated" color="#ffff00"/>
    <highlighter class="connection" color="#00ffff"/>
    <highlighter class="hypothesized" color="#ffff00"/>
    <highlighter class="preliminary" color="#ffff00"/>
    <highlighter class="it_is_thought" color="#ffff00"/>
    <highlighter class="dependent" color="#00ffff"/>
    <highlighter class="still" color="#00ffff"/>
    <highlighter class="future_analyses" color="#ccffcc"/>
    <highlighter class="goal" color="#ff6600"/>
    <highlighter class="inconclusive" color="#ffcccc"/>
    <highlighter class="ominous" color="#ccffcc"/>
    <highlighter class="studies_are_needed" color="#ccffcc"/>
    <highlighter class="linking" color="#ffff00"/>
    <highlighter class="0_urgent_call_to_action" color="#ccffcc"/>
    <highlighter class="focusing" color="#00ffff"/>
    <highlighter class="ironically" color="#ccccff"/>
    <highlighter class="aimed" color="#ff6600"/>
    <highlighter class="could_be" color="#ffff00"/>
    <highlighter class="unresolved" color="#ffcccc"/>
    <highlighter class="insight" color="#ffff00"/>
    <highlighter class="is_warranted" color="#ccffcc"/>
    <highlighter class="more_studies" color="#ccffcc"/>
    <highlighter class="one_study" color="#00ffff"/>
    <highlighter class="discrepancy" color="#ffcccc"/>
    <highlighter class="must_be_explored" color="#ccffcc"/>
    <highlighter class="should_not_be" color="#ccffcc"/>
    <highlighter class="still_being_discovered" color="#ffff00"/>
    <highlighter class="relate" color="#ffff00"/>
    <highlighter class="discrepancies" color="#ffcccc"/>
    <highlighter class="no_prior_study" color="#ffff00"/>
    <highlighter class="stated" color="#00ffff"/>
    <highlighter class="theory" color="#ffff00"/>
    <highlighter class="crucially" color="#00ffff"/>
    <highlighter class="confounded" color="#00ffff"/>
    <highlighter class="0_alternative_options" color="#ffff00"/>
    <highlighter class="research_attention" color="#ffff00"/>
    <highlighter class="absence_of" color="#00ffff"/>
    <highlighter class="0_model" color="#ffff00"/>
    <highlighter class="unsuccessful" color="#00ffff"/>
    <highlighter class="has_repeatedly_been" color="#ffff00"/>
    <highlighter class="absence_of...evidence" color="#ffff00"/>
    <highlighter class="variability" color="#ffcccc"/>
    <highlighter class="not_adequate" color="#ffff00"/>
    <highlighter class="need_for_further_investigation" color="#ccffcc"/>
    <highlighter class="believed" color="#ffff00"/>
    <highlighter class="demonstrated" color="#00ffff"/>
    <highlighter class="very_little_is_known" color="#ffff00"/>
    <highlighter class="dispute" color="#ffcccc"/>
    <highlighter class="remain_inconsistent" color="#ffcccc"/>
    <highlighter class="could" color="#ffff00"/>
    <highlighter class="observation" color="#00ffff"/>
    <highlighter class="data...is_sparse" color="#ffff00"/>
    <highlighter class="has_not_yet_been_comprehensively_evaluated" color="#ffff00"/>
    <highlighter class="multifactorial" color="#00ffff"/>
    <highlighter class="only_explain_part" color="#ffff00"/>
    <highlighter class="whether...or...or" color="#ffff00"/>
    <highlighter class="further_trials" color="#ccffcc"/>
    <highlighter class="first_study" color="#ffff00"/>
    <highlighter class="suggest" color="#00ffff"/>
    <highlighter class="suspect" color="#00ffff"/>
    <highlighter class="affected" color="#ffff00"/>
    <highlighter class="in_spite" color="#ccccff"/>
    <highlighter class="confounder" color="#00ffff"/>
    <highlighter class="expect" color="#ccffcc"/>
    <highlighter class="difficult" color="#ffcccc"/>
    <highlighter class="believed" color="#ffff00"/>
    <highlighter class="appearance" color="#ccccff"/>
    <highlighter class="highlights" color="#00ffff"/>
    <highlighter class="less_clear" color="#ffff00"/>
    <highlighter class="profound_implications" color="#ccffcc"/>
    <highlighter class="still_very_scarce" color="#ffff00"/>
    <highlighter class="further_studied" color="#ccffcc"/>
    <highlighter class="based_on" color="#00ffff"/>
    <highlighter class="cannot" color="#00ffff"/>
    <highlighter class="still_being_elucidated" color="#ffff00"/>
    <highlighter class="prone" color="#00ffff"/>
    <highlighter class="scarce" color="#ffff00"/>
    <highlighter class="first" color="#00ffff"/>
    <highlighter class="clues" color="#ffff00"/>
    <highlighter class="necessitate_further_research" color="#ccffcc"/>
    <highlighter class="confounding" color="#00ffff"/>
    <highlighter class="progress_is_needed" color="#ccffcc"/>
    <highlighter class="preferably" color="#00ffff"/>
    <highlighter class="more_work_is_needed" color="#ccffcc"/>
    <highlighter class="theoretical" color="#00ffff"/>
    <highlighter class="many_studies" color="#ffff00"/>
    <highlighter class="suggests" color="#ffff00"/>
    <highlighter class="starting_point" color="#ffff00"/>
    <highlighter class="long-term_studies" color="#ccffcc"/>
    <highlighter class="growing" color="#ffff00"/>
    <highlighter class="accounted_for" color="#00ffff"/>
    <highlighter class="surprisingly" color="#00ffff"/>
    <highlighter class="should" color="#ccffcc"/>
    <highlighter class="only" color="#00ffff"/>
    <highlighter class="consequences" color="#00ffff"/>
    <highlighter class="this...study" color="#00ffff"/>
    <highlighter class="but" color="#00ffff"/>
    <highlighter class="previous...studies" color="#ffff00"/>
    <highlighter class="possible" color="#ffff00"/>
    <highlighter class="important_to_note" color="#00ffff"/>
    <highlighter class="demonstrates" color="#00ffff"/>
    <highlighter class="set_out" color="#ff6600"/>
    <highlighter class="in_order_to" color="#00ffff"/>
    <highlighter class="unsettled" color="#ffcccc"/>
    <highlighter class="proposes" color="#ffff00"/>
    <highlighter class="accepted" color="#00ffff"/>
    <highlighter class="failed" color="#00ffff"/>
    <highlighter class="smaller...studies" color="#00ffff"/>
    <highlighter class="better_understand" color="#ffff00"/>
    <highlighter class="there_was_no" color="#00ffff"/>
    <highlighter class="needs_to_be_studied" color="#ccffcc"/>
    <highlighter class="continue_to_explore" color="#ccffcc"/>
    <highlighter class="questions" color="#ffff00"/>
    <highlighter class="proposed" color="#ffff00"/>
    <highlighter class="further_investigations" color="#ccffcc"/>
    <highlighter class="safe" color="#00ffff"/>
    <highlighter class="opens_new_opportunities" color="#ccffcc"/>
    <highlighter class="other...hypothesis" color="#ffff00"/>
    <highlighter class="has_not_been_rigorously_evaluated" color="#ffff00"/>
    <highlighter class="seems" color="#ccccff"/>
    <highlighter class="at_least" color="#ffff00"/>
    <highlighter class="potentially" color="#00ffff"/>
    <highlighter class="here" color="#ff6600"/>
    <highlighter class="problem_complication" color="#00ffff"/>
    <highlighter class="challenges" color="#ffcccc"/>
    <highlighter class="purpose" color="#ff6600"/>
    <highlighter class="advice" color="#00ffff"/>
    <highlighter class="link" color="#ffff00"/>
    <highlighter class="pressing_need" color="#ccffcc"/>
    <highlighter class="interact" color="#00ffff"/>
    <highlighter class="to_understand_better" color="#ffff00"/>
    <highlighter class="initially_thought" color="#ffcccc"/>
    <highlighter class="error" color="#ffcccc"/>
    <highlighter class="for_this_reason" color="#00ffff"/>
    <highlighter class="seemingly" color="#ccccff"/>
    <highlighter class="due...to" color="#00ffff"/>
    <highlighter class="aware" color="#00ffff"/>
    <highlighter class="impacts" color="#ffff00"/>
    <highlighter class="can" color="#00ffff"/>
    <highlighter class="validated" color="#00ffff"/>
    <highlighter class="recent_emergence" color="#ffff00"/>
    <highlighter class="observations" color="#00ffff"/>
    <highlighter class="predictor" color="#00ffff"/>
    <highlighter class="there_are_no" color="#00ffff"/>
    <highlighter class="not_very_clear" color="#ffff00"/>
    <highlighter class="mediated" color="#00ffff"/>
    <highlighter class="need_for_additional_studies" color="#ccffcc"/>
    <highlighter class="depends_on" color="#00ffff"/>
    <highlighter class="aims" color="#ff6600"/>
    <highlighter class="existing_data" color="#ffff00"/>
    <highlighter class="limited" color="#ffff00"/>
    <highlighter class="will" color="#00ffff"/>
    <highlighter class="previously_shown" color="#ffff00"/>
    <highlighter class="although" color="#ccccff"/>
    <highlighter class="gap" color="#ffff00"/>
    <highlighter class="have_to_be" color="#ccffcc"/>
    <highlighter class="issue" color="#ffcccc"/>
    <highlighter class="inadequately_studied" color="#ffff00"/>
    <highlighter class="instead" color="#00ffff"/>
    <highlighter class="no_previous_study" color="#ffff00"/>
    <highlighter class="little_insight" color="#ffff00"/>
    <highlighter class="controversy" color="#00ffff"/>
    <highlighter class="ultimately" color="#ccffcc"/>
    <highlighter class="factors" color="#00ffff"/>
    <highlighter class="contrasting" color="#ffcccc"/>
    <highlighter class="it_is_known" color="#ffff00"/>
    <highlighter class="variable" color="#00ffff"/>
    <highlighter class="challenge" color="#ffcccc"/>
    <highlighter class="independently" color="#00ffff"/>
    <highlighter class="future_interventions" color="#00ffff"/>
    <highlighter class="warrants" color="#ccffcc"/>
    <highlighter class="encouraged" color="#00ffff"/>
    <highlighter class="tends" color="#00ffff"/>
  </profile>
</knowtator-project>
